age_dijkstra/VERSION.py
age_dijkstra/__init__.py
apache_age_dijkstra-0.2.2.dist-info/LICENSE.txt
apache_age_dijkstra-0.2.2.dist-info/METADATA
apache_age_dijkstra-0.2.2.dist-info/WHEEL
apache_age_dijkstra-0.2.2.dist-info/top_level.txt
apache_age_dijkstra-0.2.2.dist-info/RECORD
