Metadata-Version: 2.1
Name: apache-age-dijkstra
Version: 0.2.2
Summary: Dijkstra shortest path algorithm using apache age graph database
Home-page: https://github.com/Munmud/apache-age-dijkstra
Author: Moontasir Mahmood
Author-email: moontasir042@gmail.com
License: Apache2.0
Keywords: Graph Database,Apache AGE,PostgreSQL,Shotrtest path,Dijkstra
Classifier: Programming Language :: Python :: 3.9
Requires-Python: >=3.9
License-File: LICENSE.txt
Requires-Dist: apache-age-python (==0.0.4)
Requires-Dist: antlr4-python3-runtime (==4.9.3)
